README.rst
setup.py
consul_owl.egg-info/PKG-INFO
consul_owl.egg-info/SOURCES.txt
consul_owl.egg-info/dependency_links.txt
consul_owl.egg-info/requires.txt
consul_owl.egg-info/top_level.txt
owl/__init__.py
owl/aio/__init__.py
owl/aio/options.py
owl/gevent/__init__.py
owl/gevent/options.py
owl/tornado/__init__.py
owl/tornado/options.py